{
  "schemaVersion": 1,
  "id": "rising_uppercut",
  "version": "${version}",

  "name": "Rising Uppercut",
  "description": "Only through conflict do we evolve.",
  "authors": [
    "MarbleGateKeeper"
  ],
  "contact": {
    "homepage": "https://www.curseforge.com/minecraft/mc-mods/rising-uppercut-fabric",
    "issues": "https://github.com/MarbleGateKeeper/RisingUppercut-Fabric/issues",
    "sources": "https://github.com/MarbleGateKeeper/RisingUppercut-Fabric",
    "author": "https://marblegate.love/"
  },

  "license": "BSD 3-Clause License",
  "icon": "assets/rising_uppercut/icon.png",
  "accessWidener": "rising_uppercut.accesswidener",
  "environment": "*",
  "entrypoints": {
    "main": [
      "love.marblegate.risinguppercut.RisingUppercut"
    ],
    "client": [
      "love.marblegate.risinguppercut.ClientSetup"
    ],
    "modmenu": [
      "love.marblegate.risinguppercut.config.ModMenuIntegration"
    ]
  },
  "mixins": [
    "rising_uppercut.mixins.json"
  ],
  "depends": {
    "fabricloader": ">=0.12.8",
    "fabric": "*",
    "minecraft": "1.18.x",
    "java": ">=17",
    "cloth-config2": ">=6.0.42"
  }
}
